cdmon_automator/__init__.py
cdmon_automator-0.0.8.dist-info/LICENSE
cdmon_automator-0.0.8.dist-info/METADATA
cdmon_automator-0.0.8.dist-info/WHEEL
cdmon_automator-0.0.8.dist-info/top_level.txt
cdmon_automator-0.0.8.dist-info/RECORD
