Metadata-Version: 2.1
Name: cdmon-automator
Version: 0.0.8
Summary: Library for CRUD operations on cdmon.com
Home-page: https://github.com/develatio/cdmon_automator
Author: Develatio
Author-email: contact@develat.io
License: UNKNOWN
Platform: UNKNOWN
Classifier: Programming Language :: Python :: 3
Classifier: License :: OSI Approved :: MIT License
Classifier: Operating System :: OS Independent
Classifier: Intended Audience :: Developers
Classifier: Intended Audience :: Information Technology
Classifier: Intended Audience :: System Administrators
Classifier: Topic :: System :: Systems Administration
Requires-Dist: selenium (==3.8.0)
Requires-Dist: python-decouple
Requires-Dist: chromedriver-binary
